bulkeditor/Certificate.txt
bulkeditor/Roboto-Bold.ttf
bulkeditor/__init__.py
bulkeditor/logo.png
bulk_editor-1.0.0.dist-info/LICENSE
bulk_editor-1.0.0.dist-info/METADATA
bulk_editor-1.0.0.dist-info/WHEEL
bulk_editor-1.0.0.dist-info/top_level.txt
bulk_editor-1.0.0.dist-info/RECORD
