Metadata-Version: 2.1
Name: bulk-editor
Version: 1.0.0
Summary: Transforming multiple certificates and images with personalized text has never been easier thanks to the all-new Image Bulk Editor.
Home-page: https://github.com/Hari-Nikesh-R/Bulk-Image-Editor
Author: Hari Nikesh R
Author-email: hari.nikesh.r.cce@gmail.com
License: UNKNOWN
Keywords: python,editor,bulk editor,certificate editor,image writer
Platform: UNKNOWN
Classifier: License :: OSI Approved :: MIT License
Classifier: Programming Language :: Python :: 3.10
Classifier: Operating System :: Unix
Classifier: Operating System :: MacOS :: MacOS X
Classifier: Operating System :: Microsoft :: Windows
Requires-Dist: opencv-python
Requires-Dist: Pillow
